[
  {
    "id": "d977cf34a2b727776a5a35732cb67fafe5388181",
    "key": "https://mp.weixin.qq.com/s/Ous-fV0xeiyDNuHaDbN8iw",
    "sourceName": "投资人六便士",
    "title": "云南采菌子的一天",
    "url": "https://mp.weixin.qq.com/s/Ous-fV0xeiyDNuHaDbN8iw",
    "createdAt": "Sat, 20 Jun 2026 08:19:53 GMT",
    "createdAtTs": 1781943593.0,
    "text": "云南采菌子的一天",
    "syncedAt": "2026-06-21T23:18:25.396480+08:00"
  },
  {
    "id": "93f892ed01068785177ca4d5b9adc0ce7eb1096a",
    "key": "https://mp.weixin.qq.com/s/MX4sDg8SMD1ZeLWPJzRnKA",
    "sourceName": "投资人六便士",
    "title": "《持cang·寄怀》",
    "url": "https://mp.weixin.qq.com/s/MX4sDg8SMD1ZeLWPJzRnKA",
    "createdAt": "Thu, 18 Jun 2026 23:03:50 GMT",
    "createdAtTs": 1781823830.0,
    "text": "《持cang·寄怀》",
    "syncedAt": "2026-06-21T23:18:25.396480+08:00"
  },
  {
    "id": "a5b636101cc86cb86db0030e81fa9940e695588b",
    "key": "https://mp.weixin.qq.com/s/JlkpEgD_DkFLZZvWFitS1A",
    "sourceName": "投资人六便士",
    "title": "苹果AI对存储的拉动",
    "url": "https://mp.weixin.qq.com/s/JlkpEgD_DkFLZZvWFitS1A",
    "createdAt": "Thu, 18 Jun 2026 01:13:30 GMT",
    "createdAtTs": 1781745210.0,
    "text": "苹果AI对存储的拉动",
    "syncedAt": "2026-06-21T23:18:25.396480+08:00"
  },
  {
    "id": "f383b80fcdb84011d3271fbbfc3c1c06bda64320",
    "key": "https://mp.weixin.qq.com/s/IZNI2Tavbx9td5gWymV4Ag",
    "sourceName": "投资人六便士",
    "title": "格局打开，才能赢麻！",
    "url": "https://mp.weixin.qq.com/s/IZNI2Tavbx9td5gWymV4Ag",
    "createdAt": "Wed, 17 Jun 2026 03:17:20 GMT",
    "createdAtTs": 1781666240.0,
    "text": "格局打开，才能赢麻！",
    "syncedAt": "2026-06-21T23:18:25.396480+08:00"
  },
  {
    "id": "05f5acd7d38c7617af83b771c84679ca6631fc2d",
    "key": "https://mp.weixin.qq.com/s/4AaWvHBXVnRLO2FSuU2XfA",
    "sourceName": "投资人六便士",
    "title": "SPCX 2.5万亿了，要FOMO吗？",
    "url": "https://mp.weixin.qq.com/s/4AaWvHBXVnRLO2FSuU2XfA",
    "createdAt": "Mon, 15 Jun 2026 23:25:39 GMT",
    "createdAtTs": 1781565939.0,
    "text": "SPCX 2.5万亿了，要FOMO吗？",
    "syncedAt": "2026-06-21T23:18:25.396480+08:00"
  },
  {
    "id": "143b6cf1b4ca270ba6faa96f27c3643addf27073",
    "key": "https://mp.weixin.qq.com/s/zgz-nY9zssVxWzB1UO3Rxw",
    "sourceName": "投资人六便士",
    "title": "毫无疑问，存储依然是唯一C位",
    "url": "https://mp.weixin.qq.com/s/zgz-nY9zssVxWzB1UO3Rxw",
    "createdAt": "Mon, 15 Jun 2026 04:11:48 GMT",
    "createdAtTs": 1781496708.0,
    "text": "毫无疑问，存储依然是唯一C位",
    "syncedAt": "2026-06-21T23:18:25.396480+08:00"
  },
  {
    "id": "d37eedb971033ede48e704b2e7f13159df6b70af",
    "key": "https://mp.weixin.qq.com/s/3oEzyaQ3QDBH1Osgl-_2OQ",
    "sourceName": "投资人六便士",
    "title": "SpaceX终于上市，到底什么价位值得击球？",
    "url": "https://mp.weixin.qq.com/s/3oEzyaQ3QDBH1Osgl-_2OQ",
    "createdAt": "Sun, 14 Jun 2026 00:03:19 GMT",
    "createdAtTs": 1781395399.0,
    "text": "SpaceX终于上市，到底什么价位值得击球？",
    "syncedAt": "2026-06-21T23:18:25.396480+08:00"
  },
  {
    "id": "c87ad8916b9d4949a2183aa7b6c97565126c2a88",
    "key": "https://mp.weixin.qq.com/s/kSAYfmQOKvtIyUGSd-HiIw",
    "sourceName": "投资人六便士",
    "title": "老川头你受的了？",
    "url": "https://mp.weixin.qq.com/s/kSAYfmQOKvtIyUGSd-HiIw",
    "createdAt": "Thu, 11 Jun 2026 23:15:20 GMT",
    "createdAtTs": 1781219720.0,
    "text": "老川头你受的了？",
    "syncedAt": "2026-06-21T23:18:25.396480+08:00"
  },
  {
    "id": "0661ca1105608e7f2c160d0987ccefdaf40c83fc",
    "key": "https://mp.weixin.qq.com/s/lFJjKCaJvKoprGcQDBjQuw",
    "sourceName": "投资人六便士",
    "title": "老川头，这么玩不合适吧？",
    "url": "https://mp.weixin.qq.com/s/lFJjKCaJvKoprGcQDBjQuw",
    "createdAt": "Thu, 11 Jun 2026 00:20:51 GMT",
    "createdAtTs": 1781137251.0,
    "text": "老川头，这么玩不合适吧？",
    "syncedAt": "2026-06-21T23:18:25.396480+08:00"
  },
  {
    "id": "4a46ed42ac5d3e7ecb3b0e2124e69a7423a490ef",
    "key": "https://mp.weixin.qq.com/s/LoDX690KYDsebn2ojrr5jQ",
    "sourceName": "投资人六便士",
    "title": "6月休息，7月再战？",
    "url": "https://mp.weixin.qq.com/s/LoDX690KYDsebn2ojrr5jQ",
    "createdAt": "Tue, 09 Jun 2026 23:20:55 GMT",
    "createdAtTs": 1781047255.0,
    "text": "6月休息，7月再战？",
    "syncedAt": "2026-06-21T23:18:25.396480+08:00"
  },
  {
    "id": "03ff3a8380857b89523b0edf2db1997d5de00fe9",
    "key": "https://mp.weixin.qq.com/s/I-KAr_dEtEwTJvD7Hn0Ppw",
    "sourceName": "击球区小能手1",
    "title": "击球区小能手1公众号文章",
    "url": "https://mp.weixin.qq.com/s/I-KAr_dEtEwTJvD7Hn0Ppw",
    "createdAt": "",
    "createdAtTs": 0.0,
    "text": "击球区小能手1公众号文章。用户手动提供的微信公众号文章链接，待补充标题和摘要。",
    "syncedAt": "2026-06-21T23:18:25.396480+08:00"
  }
]